evostrat/__init__.py
evostrat/categorical_population.py
evostrat/gmm_population.py
evostrat/individual.py
evostrat/multivariate_normal_population.py
evostrat/normal_population.py
evostrat/population.py
evostrat/util.py
evostrat/examples/__init__.py
evostrat/examples/binary_lunar_lander.py
evostrat/examples/gmm_lunar_lander.py
evostrat/examples/iterable_wrapper.py
evostrat/examples/lunar_lander.py
evostrat/examples/multivariate_normal_lunar_lander.py
evostrat/examples/normal_lunar_lander.py
evostrat/examples/normal_mnist.py
test/__init__.py
test/test_gmm_population.py
evostrat-1.4.3.dist-info/LICENSE
evostrat-1.4.3.dist-info/METADATA
evostrat-1.4.3.dist-info/WHEEL
evostrat-1.4.3.dist-info/top_level.txt
evostrat-1.4.3.dist-info/RECORD
