Metadata-Version: 2.1
Name: evostrat
Version: 1.4.3
Summary: A library that makes Evolutionary Strategies (ES) simple to use.
Home-page: https://github.com/rasmusbergpalm/evostrat
Author: Rasmus Berg Palm
Author-email: rasmusbergpalm@gmail.com
License: UNKNOWN
Platform: UNKNOWN
Classifier: Programming Language :: Python :: 3
Classifier: License :: OSI Approved :: MIT License
Classifier: Operating System :: OS Independent
Requires-Dist: torch (>=1.7.0)
